{
  "sprint": {
    "1svev1eag25s7t7hl4strr5v1k": {
      "summary": "buy string cleaner",
      "start": {
        "date": "2016-04-11"
      }
    },
    "6kk7906qrf6h501vjekd8bs1uo_20160313": {
      "summary": "Backup comp",
      "start": {
        "date": "2016-04-11"
      }
    },
    "73uqu1pgh2jf8n30t5gijn2pjo_20160406": {
      "summary": "ask mom about her job or other things ( Optional )",
      "start": {
        "date": "2016-04-11"
      }
    },
    "ceqrd1sm3mfqr16hf5b253l9so_20160403": {
      "summary": "call nana nono",
      "start": {
        "date": "2016-04-11"
      }
    },
    "me7holeib80s87272spl3rsnv8": {
      "summary": "buy strap locks",
      "start": {
        "date": "2016-04-11"
      }
    },
    "puj7r5ggqlom7b8v94tjq5mu48": {
      "summary": "Copy out guitar notes.",
      "start": {
        "date": "2016-04-11"
      }
    },
    "taqirqieggmvdr9r4da3c67fis_20160325": {
      "summary": "ask mom about biking",
      "start": {
        "date": "2016-04-11"
      }
    },
    "tpsna9fgtttj6p4av22qna4trs_20160330": {
      "summary": "Ask mom how her weekend was ( optional )",
      "start": {
        "date": "2016-04-11"
      }
    }
  },
  "backlog": {
    "48q2raihmfkfbbodu4hp0f1fhs_20160412T010000Z": {
      "summary": "Wes guitar lesson ( 45 S. Turner )",
      "start": {
        "dateTime": "2016-04-11T18:00:00-07:00",
        "timeZone": "America/Los_Angeles"
      }
    },
    "3l1mr97gdfr09p3jrtshc86rd0_20160331": {
      "summary": "Message someone from my \"people to keep in touch with\" list",
      "start": {
        "date": "2016-04-12"
      }
    },
    "3l1mr97gdfr09p3jrtshc86rd0_20160412": {
      "summary": "Message someone from my \"people to keep in touch with\" list",
      "start": {
        "date": "2016-04-12"
      }
    },
    "4d3hhpae0ftsqh6ns2dqo86rm4_20160410": {
      "summary": "Text Zach",
      "start": {
        "date": "2016-04-12"
      }
    },
    "6m3qpd13m7s3b8ee9mjf4e4vfc": {
      "summary": "Ask Mary about apartment looking at",
      "start": {
        "date": "2016-04-12"
      }
    },
    "9bbig8h0btarke0nkm1erk5q5k": {
      "summary": "talk to dave about work term report presentiation",
      "start": {
        "date": "2016-04-12"
      }
    },
    "9pghtu366nus90m8ks6t2i81ak_20160408": {
      "summary": "Call Dad",
      "start": {
        "date": "2016-04-12"
      }
    },
    "fcm9hncksnigt4ckma47n6pej0": {
      "summary": "Research getting Velcro off without destroying blinds",
      "start": {
        "date": "2016-04-12"
      }
    },
    "k1id4e3cm2fs6t435t9q8j3774": {
      "summary": "There is no substance behind sex. What does that mean?",
      "start": {
        "date": "2016-04-12"
      }
    },
    "s41e70dn8thqmn4vuro5fth96s": {
      "summary": "tell elena to tell the school about the girl who needs therapy",
      "start": {
        "date": "2016-04-12"
      }
    },
    "taqirqieggmvdr9r4da3c67fis_20160412": {
      "summary": "ask mom about biking",
      "start": {
        "date": "2016-04-12"
      }
    },
    "u8jnf7kcf8hfvrv4tihpa1d98k": {
      "summary": "Give Brett job acceptance",
      "start": {
        "date": "2016-04-12"
      }
    }
  }
}